data_fetcher/__init__.py
data_fetcher/data.py
tests/__init__.py
tests/data_tests.py
data_fetcher-0.1.8.1.dist-info/METADATA
data_fetcher-0.1.8.1.dist-info/WHEEL
data_fetcher-0.1.8.1.dist-info/entry_points.txt
data_fetcher-0.1.8.1.dist-info/top_level.txt
data_fetcher-0.1.8.1.dist-info/RECORD
