Metadata-Version: 2.1
Name: data-fetcher
Version: 0.1.8.1
Requires-Python: >=3.6
Requires-Dist: ccxt
Requires-Dist: pandas
Requires-Dist: numpy
Requires-Dist: alpaca-trade-api
Requires-Dist: alpaca-py
Requires-Dist: python-dateutil
